CMakeLists.txt
LICENSE
MANIFEST.in
README.md
pyproject.toml
requirements.txt
setup.cfg
setup.py
_skbuild/linux-x86_64-3.8/cmake-install/hdlConvertor/__init__.py
_skbuild/linux-x86_64-3.8/cmake-install/hdlConvertor/_hdlConvertor.cpython-38-x86_64-linux-gnu.so
grammars/sv2017Lexer.g4
grammars/sv2017Parser.g4
grammars/verilogPreprocLexer.g4
grammars/verilogPreprocParser.g4
grammars/vhdlLexer.g4
grammars/vhdlParser.g4
grammars/java/sv2017Lexer.g4
hdlConvertor/CMakeLists.txt
hdlConvertor/__init__.py
hdlConvertor/_hdlConvertor.pyx
hdlConvertor/python_ver_independent_str.pyx
hdlConvertor/toPy.cpp
hdlConvertor/toPy.h
hdlConvertor/toPy_expr.cpp
hdlConvertor/toPy_statements.cpp
hdlConvertor/toPy_type.cpp
hdlConvertor/verilogPreproc.pyx
hdlConvertor.egg-info/PKG-INFO
hdlConvertor.egg-info/SOURCES.txt
hdlConvertor.egg-info/dependency_links.txt
hdlConvertor.egg-info/not-zip-safe
hdlConvertor.egg-info/requires.txt
hdlConvertor.egg-info/top_level.txt
include/hdlConvertor/conversion_exception.h
include/hdlConvertor/createObject.h
include/hdlConvertor/encodingConversions.h
include/hdlConvertor/hdlConvertor.h
include/hdlConvertor/language.h
include/hdlConvertor/notImplementedLogger.h
include/hdlConvertor/parserContainer.h
include/hdlConvertor/syntaxErrorLogger.h
include/hdlConvertor/toString.h
include/hdlConvertor/universal_fs.h
include/hdlConvertor/baseHdlParser/baseHdlParser.h
include/hdlConvertor/hdlAst/bigInteger.h
include/hdlConvertor/hdlAst/codePosition.h
include/hdlConvertor/hdlAst/hdlCompInst.h
include/hdlConvertor/hdlAst/hdlContext.h
include/hdlConvertor/hdlAst/hdlDirection.h
include/hdlConvertor/hdlAst/hdlFunctionDef.h
include/hdlConvertor/hdlAst/hdlIdDef.h
include/hdlConvertor/hdlAst/hdlLibrary.h
include/hdlConvertor/hdlAst/hdlModuleDec.h
include/hdlConvertor/hdlAst/hdlModuleDef.h
include/hdlConvertor/hdlAst/hdlNamespace.h
include/hdlConvertor/hdlAst/hdlOp.h
include/hdlConvertor/hdlAst/hdlOpType.h
include/hdlConvertor/hdlAst/hdlStmAssign.h
include/hdlConvertor/hdlAst/hdlStmBlock.h
include/hdlConvertor/hdlAst/hdlStmCase.h
include/hdlConvertor/hdlAst/hdlStmExpr.h
include/hdlConvertor/hdlAst/hdlStmFor.h
include/hdlConvertor/hdlAst/hdlStmIf.h
include/hdlConvertor/hdlAst/hdlStmProcess.h
